dashem.py
dashem_native.cpython-311-x86_64-linux-gnu.so
dash_em-1.0.1.dist-info/WHEEL
dash_em-1.0.1.dist-info/top_level.txt
dash_em-1.0.1.dist-info/METADATA
dash_em-1.0.1.dist-info/RECORD
