Metadata-Version: 2.4
Name: dash-em
Version: 1.0.1
Summary: Enterprise-Grade Em-Dash Removal Library — SIMD-Accelerated String Processing
Author-email: Gaurav Gosain <itsgauravgosain@gmail.com>
License: MIT
Project-URL: Homepage, https://github.com/Gaurav-Gosain/dash-em#readme
Project-URL: Documentation, https://github.com/Gaurav-Gosain/dash-em#readme
Project-URL: Repository, https://github.com/Gaurav-Gosain/dash-em.git
Project-URL: Issues, https://github.com/Gaurav-Gosain/dash-em/issues
Keywords: em-dash,string,simd,performance,unicode,native
Classifier: Development Status :: 5 - Production/Stable
Classifier: Intended Audience :: Developers
Classifier: License :: OSI Approved :: MIT License
Classifier: Operating System :: OS Independent
Classifier: Programming Language :: C
Classifier: Programming Language :: Python :: 3
Classifier: Programming Language :: Python :: 3.10
Classifier: Programming Language :: Python :: 3.11
Classifier: Programming Language :: Python :: 3.12
Classifier: Programming Language :: Python :: 3.13
Classifier: Programming Language :: Python :: 3.14
Classifier: Topic :: Software Development :: Libraries :: Python Modules
Classifier: Topic :: Text Processing
Requires-Python: >=3.10
